deez.py
deezing-0.17.dist-info/METADATA
deezing-0.17.dist-info/WHEEL
deezing-0.17.dist-info/entry_points.txt
deezing-0.17.dist-info/top_level.txt
deezing-0.17.dist-info/RECORD
